{
    "iterations": [
        {
            "iteration_number": null,
            "mask_shown": null,
            "pattern_underlying": null,
            "level": null,
            "visibility": null,
            "flipped_bits": null,
            "accuracy": null,
            "pattern_identified": null,
            "human_button": null
        },
        {
            "iteration_number": 1,
            "mask_shown": "1_image_4_covered_0.4.png",
            "pattern_underlying": 2,
            "level": null,
            "visibility": 0.4,
            "flipped_bits": 38,
            "pattern_identified": 5,
            "accuracy": 0.9619140625,
            "human_button": 5
        },
        {
            "iteration_number": 2,
            "mask_shown": "2_image_6_covered_0.25.png",
            "pattern_underlying": 3,
            "level": null,
            "visibility": 0.25,
            "flipped_bits": 282,
            "pattern_identified": 4,
            "accuracy": 0.7197265625,
            "human_button": 4
        },
        {
            "iteration_number": 3,
            "mask_shown": "3_image_8_covered_0.2.png",
            "pattern_underlying": 4,
            "level": null,
            "visibility": 0.2,
            "flipped_bits": 220,
            "pattern_identified": 4,
            "accuracy": 0.7900390625,
            "human_button": 4
        },
        {
            "iteration_number": 4,
            "mask_shown": "4_image_4_covered_0.75.png",
            "pattern_underlying": 2,
            "level": null,
            "visibility": 0.75,
            "flipped_bits": 80,
            "pattern_identified": 2,
            "accuracy": 0.91796875,
            "human_button": 2
        },
        {
            "iteration_number": 5,
            "mask_shown": "5_image_4_covered_0.25.png",
            "pattern_underlying": 2,
            "level": null,
            "visibility": 0.25,
            "flipped_bits": 239,
            "pattern_identified": 2,
            "accuracy": 0.7919921875,
            "human_button": 2
        },
        {
            "iteration_number": 6,
            "mask_shown": "6_image_6_covered_0.8.png",
            "pattern_underlying": 3,
            "level": null,
            "visibility": 0.8,
            "flipped_bits": 100,
            "pattern_identified": 3,
            "accuracy": 0.94921875,
            "human_button": 3
        },
        {
            "iteration_number": 7,
            "mask_shown": "7_image_6_covered_0.8.png",
            "pattern_underlying": 3,
            "level": null,
            "visibility": 0.8,
            "flipped_bits": 72,
            "pattern_identified": 3,
            "accuracy": 0.9580078125,
            "human_button": 3
        },
        {
            "iteration_number": 8,
            "mask_shown": "8_image_10_covered_0.4.png",
            "pattern_underlying": 5,
            "level": null,
            "visibility": 0.4,
            "flipped_bits": 162,
            "pattern_identified": 5,
            "accuracy": 0.869140625,
            "human_button": 5
        },
        {
            "iteration_number": 9,
            "mask_shown": "9_image_8_covered_0.2.png",
            "pattern_underlying": 4,
            "level": null,
            "visibility": 0.2,
            "flipped_bits": 257,
            "pattern_identified": 5,
            "accuracy": 0.8251953125,
            "human_button": 5
        },
        {
            "iteration_number": 10,
            "mask_shown": "10_image_4_covered_0.35.png",
            "pattern_underlying": 2,
            "level": null,
            "visibility": 0.35,
            "flipped_bits": 253,
            "pattern_identified": 2,
            "accuracy": 0.80078125,
            "human_button": 2
        },
        {
            "iteration_number": 11,
            "mask_shown": "11_image_10_covered_0.8.png",
            "pattern_underlying": 5,
            "level": null,
            "visibility": 0.8,
            "flipped_bits": 84,
            "pattern_identified": 5,
            "accuracy": 0.9267578125,
            "human_button": 5
        },
        {
            "iteration_number": 12,
            "mask_shown": "12_image_10_covered_0.3.png",
            "pattern_underlying": 5,
            "level": null,
            "visibility": 0.3,
            "flipped_bits": 165,
            "pattern_identified": 5,
            "accuracy": 0.8623046875,
            "human_button": 5
        },
        {
            "iteration_number": 13,
            "mask_shown": "13_image_4_covered_0.25.png",
            "pattern_underlying": 2,
            "level": null,
            "visibility": 0.25,
            "flipped_bits": 252,
            "pattern_identified": 2,
            "accuracy": 0.783203125,
            "human_button": 2
        },
        {
            "iteration_number": 14,
            "mask_shown": "14_image_8_covered_0.75.png",
            "pattern_underlying": 4,
            "level": null,
            "visibility": 0.75,
            "flipped_bits": 129,
            "pattern_identified": 4,
            "accuracy": 0.9091796875,
            "human_button": 4
        },
        {
            "iteration_number": 15,
            "mask_shown": "15_image_4_covered_0.8.png",
            "pattern_underlying": 2,
            "level": null,
            "visibility": 0.8,
            "flipped_bits": 93,
            "pattern_identified": 2,
            "accuracy": 0.92578125,
            "human_button": 2
        },
        {
            "iteration_number": 16,
            "mask_shown": "16_image_6_covered_0.1.png",
            "pattern_underlying": 3,
            "level": null,
            "visibility": 0.1,
            "flipped_bits": 251,
            "pattern_identified": 5,
            "accuracy": 0.7705078125,
            "human_button": 5
        },
        {
            "iteration_number": 17,
            "mask_shown": "17_image_4_covered_0.65.png",
            "pattern_underlying": 2,
            "level": null,
            "visibility": 0.65,
            "flipped_bits": 137,
            "pattern_identified": 2,
            "accuracy": 0.919921875,
            "human_button": 2
        },
        {
            "iteration_number": 18,
            "mask_shown": "18_image_4_covered_0.15.png",
            "pattern_underlying": 2,
            "level": null,
            "visibility": 0.15,
            "flipped_bits": 260,
            "pattern_identified": 2,
            "accuracy": 0.7734375,
            "human_button": 2
        },
        {
            "iteration_number": 19,
            "mask_shown": "19_image_8_covered_0.1.png",
            "pattern_underlying": 4,
            "level": null,
            "visibility": 0.1,
            "flipped_bits": 249,
            "pattern_identified": 5,
            "accuracy": 0.79296875,
            "human_button": 5
        },
        {
            "iteration_number": 20,
            "mask_shown": "20_image_6_covered_0.3.png",
            "pattern_underlying": 3,
            "level": null,
            "visibility": 0.3,
            "flipped_bits": 254,
            "pattern_identified": 3,
            "accuracy": 0.802734375,
            "human_button": 3
        },
        {
            "iteration_number": 21,
            "mask_shown": "21_image_4_covered_0.75.png",
            "pattern_underlying": 2,
            "level": null,
            "visibility": 0.75,
            "flipped_bits": 93,
            "pattern_identified": 2,
            "accuracy": 0.92578125,
            "human_button": 2
        },
        {
            "iteration_number": 22,
            "mask_shown": "22_image_2_covered_0.7.png",
            "pattern_underlying": 1,
            "level": null,
            "visibility": 0.7,
            "flipped_bits": 142,
            "pattern_identified": 1,
            "accuracy": 0.8671875,
            "human_button": 1
        },
        {
            "iteration_number": 23,
            "mask_shown": "23_image_6_covered_0.6.png",
            "pattern_underlying": 3,
            "level": null,
            "visibility": 0.6,
            "flipped_bits": 127,
            "pattern_identified": 3,
            "accuracy": 0.92578125,
            "human_button": 3
        },
        {
            "iteration_number": 24,
            "mask_shown": "24_image_8_covered_0.55.png",
            "pattern_underlying": 4,
            "level": null,
            "visibility": 0.55,
            "flipped_bits": 188,
            "pattern_identified": 4,
            "accuracy": 0.87109375,
            "human_button": 4
        },
        {
            "iteration_number": 25,
            "mask_shown": "25_image_6_covered_0.3.png",
            "pattern_underlying": 3,
            "level": null,
            "visibility": 0.3,
            "flipped_bits": 225,
            "pattern_identified": 3,
            "accuracy": 0.8603515625,
            "human_button": 3
        },
        {
            "iteration_number": 26,
            "mask_shown": "26_image_6_covered_0.25.png",
            "pattern_underlying": 3,
            "level": null,
            "visibility": 0.25,
            "flipped_bits": 263,
            "pattern_identified": 3,
            "accuracy": 0.76953125,
            "human_button": 3
        },
        {
            "iteration_number": 27,
            "mask_shown": "27_image_2_covered_0.7.png",
            "pattern_underlying": 1,
            "level": null,
            "visibility": 0.7,
            "flipped_bits": 91,
            "pattern_identified": 1,
            "accuracy": 0.908203125,
            "human_button": 1
        },
        {
            "iteration_number": 28,
            "mask_shown": "28_image_8_covered_0.75.png",
            "pattern_underlying": 4,
            "level": null,
            "visibility": 0.75,
            "flipped_bits": 139,
            "pattern_identified": 4,
            "accuracy": 0.9052734375,
            "human_button": 4
        },
        {
            "iteration_number": 29,
            "mask_shown": "29_image_4_covered_0.15.png",
            "pattern_underlying": 2,
            "level": null,
            "visibility": 0.15,
            "flipped_bits": 267,
            "pattern_identified": 5,
            "accuracy": 0.7666015625,
            "human_button": 5
        },
        {
            "iteration_number": 30,
            "mask_shown": "30_image_6_covered_0.4.png",
            "pattern_underlying": 3,
            "level": null,
            "visibility": 0.4,
            "flipped_bits": 235,
            "pattern_identified": 3,
            "accuracy": 0.791015625,
            "human_button": 3
        },
        {
            "iteration_number": 31,
            "mask_shown": "31_image_2_covered_0.1.png",
            "pattern_underlying": 1,
            "level": null,
            "visibility": 0.1,
            "flipped_bits": 250,
            "pattern_identified": 1,
            "accuracy": 0.8125,
            "human_button": 1
        }
    ]
}